fhirclient/__init__.py
fhirclient/_utils.py
fhirclient/auth.py
fhirclient/client.py
fhirclient/server.py
fhirclient/models/__init__.py
fhirclient/models/account.py
fhirclient/models/activitydefinition.py
fhirclient/models/address.py
fhirclient/models/adverseevent.py
fhirclient/models/age.py
fhirclient/models/allergyintolerance.py
fhirclient/models/annotation.py
fhirclient/models/appointment.py
fhirclient/models/appointmentresponse.py
fhirclient/models/attachment.py
fhirclient/models/auditevent.py
fhirclient/models/backboneelement.py
fhirclient/models/basic.py
fhirclient/models/binary.py
fhirclient/models/biologicallyderivedproduct.py
fhirclient/models/bodystructure.py
fhirclient/models/bundle.py
fhirclient/models/capabilitystatement.py
fhirclient/models/careplan.py
fhirclient/models/careteam.py
fhirclient/models/catalogentry.py
fhirclient/models/chargeitem.py
fhirclient/models/chargeitemdefinition.py
fhirclient/models/claim.py
fhirclient/models/claimresponse.py
fhirclient/models/clinicalimpression.py
fhirclient/models/codeableconcept.py
fhirclient/models/codesystem.py
fhirclient/models/coding.py
fhirclient/models/communication.py
fhirclient/models/communicationrequest.py
fhirclient/models/compartmentdefinition.py
fhirclient/models/composition.py
fhirclient/models/conceptmap.py
fhirclient/models/condition.py
fhirclient/models/consent.py
fhirclient/models/contactdetail.py
fhirclient/models/contactpoint.py
fhirclient/models/contract.py
fhirclient/models/contributor.py
fhirclient/models/count.py
fhirclient/models/coverage.py
fhirclient/models/coverageeligibilityrequest.py
fhirclient/models/coverageeligibilityresponse.py
fhirclient/models/datarequirement.py
fhirclient/models/detectedissue.py
fhirclient/models/device.py
fhirclient/models/devicedefinition.py
fhirclient/models/devicemetric.py
fhirclient/models/devicerequest.py
fhirclient/models/deviceusestatement.py
fhirclient/models/diagnosticreport.py
fhirclient/models/distance.py
fhirclient/models/documentmanifest.py
fhirclient-4.3.2.dist-info/licenses/LICENSE
fhirclient-4.3.2.dist-info/WHEEL
fhirclient-4.3.2.dist-info/METADATA
fhirclient-4.3.2.dist-info/RECORD
