Metadata-Version: 2.4
Name: fhirclient
Version: 4.3.2
Summary: A flexible client for FHIR servers supporting the SMART on FHIR protocol
Keywords: smart,fhir,healthcare,medical-informatics,clinical-informatics,biomedical-informatics
Author-email: SMART Platforms Team <support@smarthealthit.org>
Requires-Python: >= 3.9
Classifier: Development Status :: 5 - Production/Stable
Classifier: Intended Audience :: Developers
Classifier: Natural Language :: English
Classifier: License :: OSI Approved :: Apache Software License
Classifier: Operating System :: OS Independent
Classifier: Programming Language :: Python
Classifier: Programming Language :: Python :: 3
Classifier: Topic :: Software Development :: Libraries :: Python Modules
License-File: LICENSE
Requires-Dist: requests >= 2.4
Requires-Dist: pytest >= 2.5 ; extra == "tests"
Requires-Dist: pytest-cov ; extra == "tests"
Requires-Dist: responses ; extra == "tests"
Project-URL: Documentation, https://docs.smarthealthit.org/client-py/
Project-URL: Homepage, https://github.com/smart-on-fhir/client-py
Provides-Extra: tests
